[
  {
    "id": "1",
    "userId": "1",
    "imageHeroBase64": "",
    "imageHeroLink": "https://i.pinimg.com/originals/2b/6b/77/2b6b7760aa3ac0228c8d6e0dc0fc377f.jpg",
    "createdAt": 1654100937547,
    "title": "Chời ơi cái quần què gì dây, ahuhuhu đồ chóa",
    "summary": "Nỗi buồn thì chắc hẳn đời người ai cũng phải có, có người buồn vì chuyện tình cảm khi cứ mãi tương tư một ai đó, có người vì khi làm việc gì cũng bị người xung quanh lên án, chỉ trích vì sốg không thực tế, cũng có người buồn vì không có được một tri kỷ để dốc lòng tâm sự, trút cạn nỗi buồn. Nỗi buồn mênh mông đến thế…",
    "content": "",
    "comment": 7,
    "love": 10,
    "isReport": false,
    "reportQuantity": 0,
    "category": ["vui-nhon", "cuoc-song"]
  },
  {
    "id": "2",
    "userId": "2",
    "imageHeroBase64": "",
    "imageHeroLink": "https://cafefcdn.com/thumb_w/650/203337114487263232/2021/8/11/photo1628641528786-16286415294652056925705.jpg",
    "createdAt": 1654135656848,
    "title": "Học từ người Do Thái bí kíp giúp tiền đẻ ra tiền",
    "summary": "Không chỉ nổi tiếng thông minh, người Do Thái còn là chủng tộc sản sinh ra rất nhiều tỷ phú trên thế giới như Larry Ellison, Michael Bloomberg, Michael Dell,... Vậy bí kíp gì giúp họ trở nên giàu có như vậy? Cùng tham khảo bài viết này ngay nhé!",
    "content": "",
    "comment": 7,
    "love": 7,
    "isReport": false,
    "reportQuantity": 0,
    "category": ["khoanh-khac", "cuoc-song", "kiem-tien"]
  },
  {
    "id": "3",
    "userId": "2",
    "imageHeroBase64": "",
    "imageHeroLink": "https://cafefcdn.com/thumb_w/650/203337114487263232/2021/8/11/photo1628641528786-16286415294652056925705.jpg",
    "createdAt": 1654136132928,
    "title": "Học từ người Do Thái bí kíp giúp tiền đẻ ra tiền",
    "summary": "Không chỉ nổi tiếng thông minh, người Do Thái còn là chủng tộc sản sinh ra rất nhiều tỷ phú trên thế giới như Larry Ellison, Michael Bloomberg, Michael Dell,... Vậy bí kíp gì giúp họ trở nên giàu có như vậy? Cùng tham khảo bài viết này ngay nhé!",
    "content": "",
    "comment": 7,
    "love": 0,
    "isReport": false,
    "reportQuantity": 0,
    "category": ["khoanh-khac", "dong-vat", "kiem-tien", "vui-nhon"]
  },
  {
    "id": "4",
    "userId": "2",
    "imageHeroBase64": "",
    "imageHeroLink": "https://cafefcdn.com/thumb_w/650/203337114487263232/2021/8/11/photo1628641528786-16286415294652056925705.jpg",
    "createdAt": 1654136132928,
    "title": "Học từ người Do Thái bí kíp giúp tiền đẻ ra tiền",
    "summary": "Không chỉ nổi tiếng thông minh, người Do Thái còn là chủng tộc sản sinh ra rất nhiều tỷ phú trên thế giới như Larry Ellison, Michael Bloomberg, Michael Dell,... Vậy bí kíp gì giúp họ trở nên giàu có như vậy? Cùng tham khảo bài viết này ngay nhé!",
    "content": "",
    "comment": 7,
    "love": 0,
    "isReport": false,
    "reportQuantity": 0,
    "category": ["khoanh-khac", "cuoc-song", "kiem-tien", "vui-nhon"]
  },
  {
    "id": "5",
    "userId": "1",
    "imageHeroBase64": "",
    "imageHeroLink": "https://i.pinimg.com/originals/2b/6b/77/2b6b7760aa3ac0228c8d6e0dc0fc377f.jpg",
    "createdAt": 1654100937547,
    "title": "Chời ơi cái quần què gì dây, ahuhuhu đồ chóa",
    "summary": "Nỗi buồn thì chắc hẳn đời người ai cũng phải có, có người buồn vì chuyện tình cảm khi cứ mãi tương tư một ai đó, có người vì khi làm việc gì cũng bị người xung quanh lên án, chỉ trích vì sốg không thực tế, cũng có người buồn vì không có được một tri kỷ để dốc lòng tâm sự, trút cạn nỗi buồn. Nỗi buồn mênh mông đến thế…",
    "content": "",
    "comment": 7,
    "love": 10,
    "isReport": false,
    "reportQuantity": 0,
    "category": ["vui-nhon", "cuoc-song", "chia-se", "vui-nhon"]
  },
  {
    "id": "6",
    "userId": "2",
    "imageHeroBase64": "",
    "imageHeroLink": "https://cafefcdn.com/thumb_w/650/203337114487263232/2021/8/11/photo1628641528786-16286415294652056925705.jpg",
    "createdAt": 1654135656848,
    "title": "Học từ người Do Thái bí kíp giúp tiền đẻ ra tiền",
    "summary": "Không chỉ nổi tiếng thông minh, người Do Thái còn là chủng tộc sản sinh ra rất nhiều tỷ phú trên thế giới như Larry Ellison, Michael Bloomberg, Michael Dell,... Vậy bí kíp gì giúp họ trở nên giàu có như vậy? Cùng tham khảo bài viết này ngay nhé!",
    "content": "",
    "comment": 7,
    "love": 7,
    "isReport": false,
    "reportQuantity": 0,
    "category": ["vui-nhon", "cuoc-song", "khac", "vui-nhon"]
  },
  {
    "id": "7",
    "userId": "1",
    "imageHeroBase64": "",
    "imageHeroLink": "https://i.pinimg.com/originals/2b/6b/77/2b6b7760aa3ac0228c8d6e0dc0fc377f.jpg",
    "createdAt": 1654100937547,
    "title": "Chời ơi cái quần què gì dây, ahuhuhu đồ chóa",
    "summary": "Nỗi buồn thì chắc hẳn đời người ai cũng phải có, có người buồn vì chuyện tình cảm khi cứ mãi tương tư một ai đó, có người vì khi làm việc gì cũng bị người xung quanh lên án, chỉ trích vì sốg không thực tế, cũng có người buồn vì không có được một tri kỷ để dốc lòng tâm sự, trút cạn nỗi buồn. Nỗi buồn mênh mông đến thế…",
    "content": "",
    "comment": 7,
    "love": 10,
    "isReport": false,
    "reportQuantity": 0,
    "category": ["vui-nhon", "chia-se", "kiem-tien", "vui-nhon"]
  },
  {
    "id": "8",
    "userId": "2",
    "imageHeroBase64": "",
    "imageHeroLink": "https://cafefcdn.com/thumb_w/650/203337114487263232/2021/8/11/photo1628641528786-16286415294652056925705.jpg",
    "createdAt": 1654135656848,
    "title": "Học từ người Do Thái bí kíp giúp tiền đẻ ra tiền",
    "summary": "Không chỉ nổi tiếng thông minh, người Do Thái còn là chủng tộc sản sinh ra rất nhiều tỷ phú trên thế giới như Larry Ellison, Michael Bloomberg, Michael Dell,... Vậy bí kíp gì giúp họ trở nên giàu có như vậy? Cùng tham khảo bài viết này ngay nhé!",
    "content": "",
    "comment": 7,
    "love": 7,
    "isReport": false,
    "reportQuantity": 0,
    "category": ["vui-nhon", "kiem-tien", "cong-nghe", "chia-se"]
  },
  {
    "id": "9",
    "userId": "2",
    "imageHeroBase64": "",
    "imageHeroLink": "https://genk.mediacdn.vn/thumb_w/640/139269124445442048/2022/6/10/an-enthusiast-turned-a-nokia-1680-feature-phone-into-a-1654835709982-16548357102352057761248.jpg",
    "createdAt": 1654914295879,
    "title": "Đam mê phần cứng, hacker độ điện thoại phổ thông Nokia 1680 thành máy tính Linux",
    "summary": "Nokia 1680 là chiếc điện thoại phổ thông ra mắt vào năm 2008, ngay trước khi smartphone bắt đầu trở thành tiêu chuẩn. Được thiết kế dành cho nghe gọi, nhắn tin với không nhiều tính năng bổ sung, chiếc điện thoại này có màn hình nhỏ, bàn phím số T9 và chỉ hỗ trợ mạng 2G.",
    "content": "",
    "comment": 0,
    "love": 9,
    "isReport": false,
    "reportQuantity": 0,
    "category": ["vui-nhon", "cong-nghe", "chia-se"]
  },
  {
    "id": "10",
    "userId": "2",
    "imageHeroBase64": "",
    "imageHeroLink": "https://genk.mediacdn.vn/139269124445442048/2022/6/11/edit-27571-1654833500726234614971-1654914085300-16549140862651340281502.jpeg",
    "createdAt": 1654914467708,
    "title": "Việt Nam nằm trong top 5 quốc gia có nhiều người sở hữu NFT nhất thế giới",
    "summary": "Theo báo cáo mới nhất của Statista, NFT nhận được sự quan tâm lớn tại nhiều quốc gia Đông Á và Đông Nam Á, trong đó có Thái Lan, Trung Quốc và Việt Nam.",
    "content": "",
    "comment": 0,
    "love": 9,
    "isReport": false,
    "reportQuantity": 0,
    "category": ["vui-nhon", "chia-se"]
  }
]
